searchcountry/__init__.py
searchcountry/info_negara.py
infonegara-0.0.1.dist-info/LICENSE.txt
infonegara-0.0.1.dist-info/METADATA
infonegara-0.0.1.dist-info/WHEEL
infonegara-0.0.1.dist-info/top_level.txt
infonegara-0.0.1.dist-info/RECORD
