Metadata-Version: 2.1
Name: infonegara
Version: 0.0.1
Summary: Library buat kasi informasi singkat negara.
Home-page: https://github.com/shaaa-xq/infonegara
Author: shaaa
Author-email: <ayeshacha177@gmail.com>
License: MIT
Keywords: info,negara
Classifier: Development Status :: 1 - Planning
License-File: LICENSE.txt
